unittest2doc/__init__.py
unittest2doc/bin.py
unittest2doc/formatter/__init__.py
unittest2doc/formatter/json_formatter.py
unittest2doc/templates.py
unittest2doc/unittest2doc.py
unittest2doc/utils/__init__.py
unittest2doc/utils/exec_tool.py
unittest2doc-0.1.2.dist-info/METADATA
unittest2doc-0.1.2.dist-info/WHEEL
unittest2doc-0.1.2.dist-info/entry_points.txt
unittest2doc-0.1.2.dist-info/RECORD
